pikpakapi/PikpakException.py
pikpakapi/__init__.py
pikpakapi/enums.py
pikpakapi/utils.py
pikpakapi-0.1.10.dist-info/METADATA
pikpakapi-0.1.10.dist-info/WHEEL
pikpakapi-0.1.10.dist-info/RECORD
