Metadata-Version: 2.1
Name: PikPakAPI
Version: 0.1.10
Summary: PikPakAPI
Home-page: https://github.com/Quan666/PikPakAPI
License: GPL-3.0-only
Keywords: pikpak,api
Author: Quan666
Author-email: i@Rori.eMail
Requires-Python: >=3.8.3,<4.0.0
Classifier: License :: OSI Approved :: GNU General Public License v3 (GPLv3)
Classifier: Programming Language :: Python :: 3
Classifier: Programming Language :: Python :: 3.9
Classifier: Programming Language :: Python :: 3.10
Classifier: Programming Language :: Python :: 3.11
Classifier: Programming Language :: Python :: 3.12
Requires-Dist: httpx (>=0.24.1)
Project-URL: Repository, https://github.com/Quan666/PikPakAPI
